jinjatomic/__init__.py
jinjatomic/jinjatomic.py
jinjatomic/py.typed
jinjatomic-0.0.2.dist-info/METADATA
jinjatomic-0.0.2.dist-info/WHEEL
jinjatomic-0.0.2.dist-info/top_level.txt
jinjatomic-0.0.2.dist-info/RECORD
