Metadata-Version: 2.4
Name: jinjatomic
Version: 0.0.2
Summary: A Datomic REST API client for Python reliant on jinja2 templates for writing stringified edn.
Home-page: https://github.com/lukal-x/jinjatomic
Author: Luka L
Requires-Dist: edn-format
Requires-Dist: jinja2
Requires-Dist: requests
Dynamic: author
Dynamic: description
Dynamic: description-content-type
Dynamic: home-page
Dynamic: requires-dist
Dynamic: summary
